LICENSE.txt
MANIFEST.in
README.rst
setup.py
jsongit/__init__.py
jsongit/api.py
jsongit/constants.py
jsongit/exceptions.py
jsongit/models.py
jsongit/utils.py
jsongit/version.py
jsongit/wrappers.py
jsongit.egg-info/PKG-INFO
jsongit.egg-info/SOURCES.txt
jsongit.egg-info/dependency_links.txt
jsongit.egg-info/requires.txt
jsongit.egg-info/top_level.txt
test/test_diff.py
test/test_log.py
test/test_repository.py
test/test_threads.py