Metadata-Version: 1.0
Name: jsongit
Version: 0.0.6
Summary: Git for JSON
Home-page: http://github.com/talos/jsongit
Author: John Krauss
Author-email: john@accursedware.com
License: BSD
Platform: UNKNOWN
Classifier: Development Status :: 3 - Alpha
Classifier: Intended Audience :: Developers
Classifier: Topic :: Software Development
Classifier: Natural Language :: English
Classifier: License :: OSI Approved :: BSD License
Classifier: Programming Language :: Python :: 2.6
Classifier: Programming Language :: Python :: 2.7
